__init__.py
tz_kst.py
tz_kst-0.5.2.dist-info/METADATA
tz_kst-0.5.2.dist-info/WHEEL
tz_kst-0.5.2.dist-info/top_level.txt
tz_kst-0.5.2.dist-info/RECORD
