Metadata-Version: 2.1
Name: tz_kst
Version: 0.5.2
Summary: This module returns current datetime in Seoul/asia
Author-email: Mingk42 <xoals123456t@gmail.com>
License: MIT
Requires-Python: >=3.11
